README.md
setup.py
pygitea/__init__.py
pygitea/resources.py
pygitea.egg-info/PKG-INFO
pygitea.egg-info/SOURCES.txt
pygitea.egg-info/dependency_links.txt
pygitea.egg-info/requires.txt
pygitea.egg-info/top_level.txt