Metadata-Version: 1.0
Name: pygitea
Version: 0.0.1
Summary: Gitea API wrapper for python
Home-page: http://github.com/jo-nas/pygitea
Author: Jonas
Author-email: jonas@steinka.mp
License: WTFPL
Platform: UNKNOWN
